timelimit/__init__.py
timelimit/_constants.py
timelimit/_timelimited.py
timelimit-0.1.0.dist-info/LICENSE
timelimit-0.1.0.dist-info/METADATA
timelimit-0.1.0.dist-info/WHEEL
timelimit-0.1.0.dist-info/top_level.txt
timelimit-0.1.0.dist-info/RECORD
