Metadata-Version: 2.1
Name: timelimit
Version: 0.1.0
Summary: Sets the time limit for slow-running functions.
Home-page: https://github.com/rtmigo/timelimit_py#readme
Author: Artёm IG
Author-email: ortemeo@gmail.com
License: MIT
Keywords: timeout,time,out,function,thread,process,threading,multiprocessing
Platform: UNKNOWN
Classifier: Development Status :: 4 - Beta
Classifier: License :: OSI Approved :: MIT License
Classifier: Programming Language :: Python :: 3.6
Classifier: Programming Language :: Python :: 3.7
Classifier: Programming Language :: Python :: 3.8
Classifier: Programming Language :: Python :: 3.9
Classifier: Operating System :: POSIX
Classifier: Operating System :: Microsoft :: Windows
